<?xml version="1.0" encoding="UTF-8"?>
<preferences>
 <debug showDebugMenu="0" />
 <systemtable filter="All Interfaces">
  <columns>
   <connections preferredWidth="127" />
   <irq preferredWidth="34" />
  </columns>
 </systemtable>
 <library
   expandedCategories="Library/Memory Interfaces and Controllers/Flash,Library/Memory Interfaces and Controllers/Memory Interfaces with UniPHY,Library/Memory Interfaces and Controllers/SDRAM,Library/Memory Interfaces and Controllers,Library,Project" />
 <window width="2785" height="1731" x="154" y="109" />
</preferences>
